<?xml version='1.0' encoding='UTF-8' standalone='yes' ?><hierarchy rotation="0"><node index="0" text="" resource-id="" class="android.widget.FrameLayout" package="com.ttkk0000.meowcircle.kmpapp" content-desc="" checkable="false" checked="false" clickable="false" enabled="true" focusable="false" focused="false" scrollable="false" long-clickable="false" password="false" selected="false" bounds="[0,0][2160,3840]"><node index="0" text="" resource-id="" class="android.widget.LinearLayout" package="com.ttkk0000.meowcircle.kmpapp" content-desc="" checkable="false" checked="false" clickable="false" enabled="true" focusable="false" focused="false" scrollable="false" long-clickable="false" password="false" selected="false" bounds="[0,0][2160,3840]"><node index="0" text="" resource-id="android:id/content" class="android.widget.FrameLayout" package="com.ttkk0000.meowcircle.kmpapp" content-desc="" checkable="false" checked="false" clickable="false" enabled="true" focusable="false" focused="false" scrollable="false" long-clickable="false" password="false" selected="false" bounds="[0,0][2160,3840]"><node index="0" text="" resource-id="" class="androidx.compose.ui.platform.ComposeView" package="com.ttkk0000.meowcircle.kmpapp" content-desc="" checkable="false" checked="false" clickable="false" enabled="true" focusable="false" focused="false" scrollable="false" long-clickable="false" password="false" selected="false" bounds="[0,0][2160,3840]"><node index="0" text="" resource-id="" class="android.view.View" package="com.ttkk0000.meowcircle.kmpapp" content-desc="" checkable="false" checked="false" clickable="false" enabled="true" focusable="false" focused="false" scrollable="false" long-clickable="false" password="false" selected="false" bounds="[0,0][2160,3840]"><node index="0" text="" resource-id="" class="android.view.View" package="com.ttkk0000.meowcircle.kmpapp" content-desc="" checkable="false" checked="false" clickable="false" enabled="true" focusable="false" focused="false" scrollable="false" long-clickable="false" password="false" selected="false" bounds="[0,0][2160,3840]"><node index="0" text="" resource-id="" class="android.view.View" package="com.ttkk0000.meowcircle.kmpapp" content-desc="" checkable="false" checked="false" clickable="true" enabled="true" focusable="true" focused="false" scrollable="false" long-clickable="false" password="false" selected="false" bounds="[21,144][265,388]"><node index="0" text="" resource-id="" class="android.view.View" package="com.ttkk0000.meowcircle.kmpapp" content-desc="返回" checkable="false" checked="false" clickable="false" enabled="true" focusable="false" focused="false" scrollable="false" long-clickable="false" password="false" selected="false" bounds="[82,205][204,286]" /><node index="1" text="" resource-id="" class="android.widget.Button" package="com.ttkk0000.meowcircle.kmpapp" content-desc="" checkable="false" checked="false" clickable="false" enabled="true" focusable="false" focused="false" scrollable="false" long-clickable="false" password="false" selected="false" bounds="[41,164][245,368]" /></node><node index="1" text="我的设置" resource-id="" class="android.widget.TextView" package="com.ttkk0000.meowcircle.kmpapp" content-desc="" checkable="false" checked="false" clickable="false" enabled="true" focusable="false" focused="false" scrollable="false" long-clickable="false" password="false" selected="false" bounds="[265,198][1895,286]" /><node index="2" text="" resource-id="" class="android.widget.ScrollView" package="com.ttkk0000.meowcircle.kmpapp" content-desc="" checkable="false" checked="false" clickable="false" enabled="true" focusable="false" focused="false" scrollable="true" long-clickable="false" password="false" selected="false" bounds="[0,408][2160,3840]"><node index="0" text="" resource-id="" class="android.view.View" package="com.ttkk0000.meowcircle.kmpapp" content-desc="" checkable="false" checked="false" clickable="false" enabled="true" focusable="false" focused="false" scrollable="false" long-clickable="false" password="false" selected="false" bounds="[82,408][2078,472]"><node NAF="true" index="0" text="" resource-id="" class="android.view.View" package="com.ttkk0000.meowcircle.kmpapp" content-desc="" checkable="false" checked="false" clickable="true" enabled="true" focusable="true" focused="false" scrollable="false" long-clickable="false" password="false" selected="false" bounds="[82,286][2078,472]" /></node><node index="1" text="偏好" resource-id="" class="android.widget.TextView" package="com.ttkk0000.meowcircle.kmpapp" content-desc="" checkable="false" checked="false" clickable="false" enabled="true" focusable="false" focused="false" scrollable="false" long-clickable="false" password="false" selected="false" bounds="[122,554][244,645]" /><node index="2" text="" resource-id="" class="android.view.View" package="com.ttkk0000.meowcircle.kmpapp" content-desc="" checkable="false" checked="false" clickable="false" enabled="true" focusable="false" focused="false" scrollable="false" long-clickable="false" password="false" selected="false" bounds="[82,686][2078,1845]"><node index="0" text="" resource-id="" class="android.view.View" package="com.ttkk0000.meowcircle.kmpapp" content-desc="" checkable="false" checked="false" clickable="true" enabled="true" focusable="true" focused="false" scrollable="false" long-clickable="false" password="false" selected="false" bounds="[82,686][2078,972]"><node index="0" text="外观与主题" resource-id="" class="android.widget.TextView" package="com.ttkk0000.meowcircle.kmpapp" content-desc="" checkable="false" checked="false" clickable="false" enabled="true" focusable="false" focused="false" scrollable="false" long-clickable="false" password="false" selected="false" bounds="[368,774][1894,885]" /></node><node index="1" text="" resource-id="" class="android.view.View" package="com.ttkk0000.meowcircle.kmpapp" content-desc="" checkable="false" checked="false" clickable="true" enabled="true" focusable="true" focused="false" scrollable="false" long-clickable="false" password="false" selected="false" bounds="[82,977][2078,1263]"><node index="0" text="功能主题" resource-id="" class="android.widget.TextView" package="com.ttkk0000.meowcircle.kmpapp" content-desc="" checkable="false" checked="false" clickable="false" enabled="true" focusable="false" focused="false" scrollable="false" long-clickable="false" password="false" selected="false" bounds="[368,1065][1894,1176]" /></node><node index="2" text="" resource-id="" class="android.view.View" package="com.ttkk0000.meowcircle.kmpapp" content-desc="" checkable="false" checked="false" clickable="true" enabled="true" focusable="true" focused="false" scrollable="false" long-clickable="false" password="false" selected="false" bounds="[82,1268][2078,1554]"><node index="0" text="通知设置" resource-id="" class="android.widget.TextView" package="com.ttkk0000.meowcircle.kmpapp" content-desc="" checkable="false" checked="false" clickable="false" enabled="true" focusable="false" focused="false" scrollable="false" long-clickable="false" password="false" selected="false" bounds="[368,1356][1894,1467]" /></node><node index="3" text="" resource-id="" class="android.view.View" package="com.ttkk0000.meowcircle.kmpapp" content-desc="" checkable="false" checked="false" clickable="true" enabled="true" focusable="true" focused="false" scrollable="false" long-clickable="false" password="false" selected="false" bounds="[82,1559][2078,1845]"><node index="0" text="语言" resource-id="" class="android.widget.TextView" package="com.ttkk0000.meowcircle.kmpapp" content-desc="" checkable="false" checked="false" clickable="false" enabled="true" focusable="false" focused="false" scrollable="false" long-clickable="false" password="false" selected="false" bounds="[368,1647][1894,1758]" /></node></node><node index="3" text="隐私与条款" resource-id="" class="android.widget.TextView" package="com.ttkk0000.meowcircle.kmpapp" content-desc="" checkable="false" checked="false" clickable="false" enabled="true" focusable="false" focused="false" scrollable="false" long-clickable="false" password="false" selected="false" bounds="[122,1927][427,2018]" /><node index="4" text="" resource-id="" class="android.view.View" package="com.ttkk0000.meowcircle.kmpapp" content-desc="" checkable="false" checked="false" clickable="false" enabled="true" focusable="false" focused="false" scrollable="false" long-clickable="false" password="false" selected="false" bounds="[82,2059][2078,2927]"><node index="0" text="" resource-id="" class="android.view.View" package="com.ttkk0000.meowcircle.kmpapp" content-desc="" checkable="false" checked="false" clickable="true" enabled="true" focusable="true" focused="false" scrollable="false" long-clickable="false" password="false" selected="false" bounds="[82,2059][2078,2345]"><node index="0" text="隐私政策" resource-id="" class="android.widget.TextView" package="com.ttkk0000.meowcircle.kmpapp" content-desc="" checkable="false" checked="false" clickable="false" enabled="true" focusable="false" focused="false" scrollable="false" long-clickable="false" password="false" selected="false" bounds="[368,2147][1894,2258]" /></node><node index="1" text="" resource-id="" class="android.view.View" package="com.ttkk0000.meowcircle.kmpapp" content-desc="" checkable="false" checked="false" clickable="true" enabled="true" focusable="true" focused="false" scrollable="false" long-clickable="false" password="false" selected="false" bounds="[82,2350][2078,2636]"><node index="0" text="用户须知" resource-id="" class="android.widget.TextView" package="com.ttkk0000.meowcircle.kmpapp" content-desc="" checkable="false" checked="false" clickable="false" enabled="true" focusable="false" focused="false" scrollable="false" long-clickable="false" password="false" selected="false" bounds="[368,2438][1894,2549]" /></node><node index="2" text="" resource-id="" class="android.view.View" package="com.ttkk0000.meowcircle.kmpapp" content-desc="" checkable="false" checked="false" clickable="true" enabled="true" focusable="true" focused="false" scrollable="false" long-clickable="false" password="false" selected="false" bounds="[82,2641][2078,2927]"><node index="0" text="社区规则" resource-id="" class="android.widget.TextView" package="com.ttkk0000.meowcircle.kmpapp" content-desc="" checkable="false" checked="false" clickable="false" enabled="true" focusable="false" focused="false" scrollable="false" long-clickable="false" password="false" selected="false" bounds="[368,2729][1894,2840]" /></node></node><node index="5" text="其他" resource-id="" class="android.widget.TextView" package="com.ttkk0000.meowcircle.kmpapp" content-desc="" checkable="false" checked="false" clickable="false" enabled="true" focusable="false" focused="false" scrollable="false" long-clickable="false" password="false" selected="false" bounds="[122,3009][244,3100]" /><node index="6" text="" resource-id="" class="android.view.View" package="com.ttkk0000.meowcircle.kmpapp" content-desc="" checkable="false" checked="false" clickable="false" enabled="true" focusable="false" focused="false" scrollable="false" long-clickable="false" password="false" selected="false" bounds="[82,3141][2078,3718]"><node index="0" text="" resource-id="" class="android.view.View" package="com.ttkk0000.meowcircle.kmpapp" content-desc="" checkable="false" checked="false" clickable="true" enabled="true" focusable="true" focused="false" scrollable="false" long-clickable="false" password="false" selected="false" bounds="[82,3141][2078,3427]"><node index="0" text="清理缓存" resource-id="" class="android.widget.TextView" package="com.ttkk0000.meowcircle.kmpapp" content-desc="" checkable="false" checked="false" clickable="false" enabled="true" focusable="false" focused="false" scrollable="false" long-clickable="false" password="false" selected="false" bounds="[368,3229][1673,3340]" /><node index="1" text="124 MB" resource-id="" class="android.widget.TextView" package="com.ttkk0000.meowcircle.kmpapp" content-desc="" checkable="false" checked="false" clickable="false" enabled="true" focusable="false" focused="false" scrollable="false" long-clickable="false" password="false" selected="false" bounds="[1673,3235][1955,3334]" /></node><node index="1" text="" resource-id="" class="android.view.View" package="com.ttkk0000.meowcircle.kmpapp" content-desc="" checkable="false" checked="false" clickable="true" enabled="true" focusable="true" focused="false" scrollable="false" long-clickable="false" password="false" selected="false" bounds="[82,3432][2078,3718]"><node index="0" text="退出登录" resource-id="" class="android.widget.TextView" package="com.ttkk0000.meowcircle.kmpapp" content-desc="" checkable="false" checked="false" clickable="false" enabled="true" focusable="false" focused="false" scrollable="false" long-clickable="false" password="false" selected="false" bounds="[368,3520][1894,3631]" /></node></node></node></node></node></node></node></node></node></hierarchy>